pinclr/__init__.py
pinclr-0.0.1.dist-info/METADATA
pinclr-0.0.1.dist-info/WHEEL
pinclr-0.0.1.dist-info/top_level.txt
pinclr-0.0.1.dist-info/RECORD
