Metadata-Version: 2.1
Name: pinclr
Version: 0.0.1
Summary: Python Client for Pinclr Common Libraries
Home-page: https://github.com/pinclr/pinclr-python
Author: Pinclr Coders
Author-email: Pinclr Coders <coding@pinclr.com>
Classifier: Programming Language :: Python :: 3
Classifier: License :: OSI Approved :: Apache Software License
Classifier: Operating System :: OS Independent
Requires-Python: >=3.10
